forx/__init__.py
forx/__main__.py
forx/convert.py
forx/currency_data.py
forx-1.0.4.dist-info/LICENSE
forx-1.0.4.dist-info/METADATA
forx-1.0.4.dist-info/WHEEL
forx-1.0.4.dist-info/entry_points.txt
forx-1.0.4.dist-info/top_level.txt
forx-1.0.4.dist-info/RECORD
