Metadata-Version: 2.1
Name: forx
Version: 1.0.4
Summary: a command line tool for checking exchange rates between currencies, both crypto and fiat.
Home-page: https://github.com/Gbox4/forx
Author: Gabe Banks
Author-email: gabriel.t.banks@gmail.com
License: UNKNOWN
Keywords: forx forex finance crypto exchange currency conversion
Platform: UNKNOWN
Classifier: Programming Language :: Python :: 3.6
Classifier: License :: OSI Approved :: GNU General Public License v3 or later (GPLv3+)
Classifier: Operating System :: OS Independent
Requires-Python: >=3.6
License-File: LICENSE
Requires-Dist: requests
